LICENSE-APACHE
LICENSE-MIT
symscan-0.7.2.dist-info/METADATA
symscan-0.7.2.dist-info/WHEEL
symscan-0.7.2.dist-info/licenses/LICENSE-APACHE
symscan-0.7.2.dist-info/licenses/LICENSE-MIT
symscan/__init__.py
symscan/__init__.pyi
symscan/py.typed
symscan/symscan.cp311-win_amd64.pyd
symscan-0.7.2.dist-info/RECORD
