Metadata-Version: 2.4
Name: symscan
Version: 0.7.2
Classifier: Development Status :: 4 - Beta
Classifier: Intended Audience :: Developers
Classifier: Intended Audience :: Science/Research
Classifier: License :: OSI Approved :: MIT License
Classifier: Operating System :: MacOS
Classifier: Operating System :: Microsoft :: Windows
Classifier: Operating System :: POSIX :: Linux
Classifier: Programming Language :: Python :: 3
Classifier: Topic :: Text Processing
Classifier: Topic :: Scientific/Engineering
Requires-Dist: numpy~=2.3
Requires-Dist: sphinx ; extra == 'dev'
Requires-Dist: esbonio ; extra == 'dev'
Requires-Dist: shibuya ; extra == 'dev'
Requires-Dist: numpydoc ; extra == 'dev'
Requires-Dist: pandas ; extra == 'dev'
Provides-Extra: dev
License-File: LICENSE-APACHE
License-File: LICENSE-MIT
Summary: Fast discovery of similar strings in bulk
Keywords: edit-distance,levenshtein-distance,string-matching,string-search,string-similarity,symspell
Home-Page: https://github.com/yutanagano/symscan
Author-email: Yuta Nagano <yutanagano51@proton.me>, Matthew Cowley <matthew.v.cowley@gmail.com>
Maintainer-email: Yuta Nagano <yutanagano51@proton.me>
Requires-Python: >=3.10
Project-URL: Homepage, https://github.com/yutanagano/symscan
Project-URL: Documentation, https://symscan.readthedocs.io
Project-URL: Repository, https://github.com/yutanagano/symscan
Project-URL: Issues, https://github.com/yutanagano/symscan/issues
